remotivelabs/topology/__init__.py
remotivelabs/topology/_docs/snippets/behavioral_model.py
remotivelabs/topology/_docs/snippets/can_namespace.py
remotivelabs/topology/_docs/snippets/can_namespace_bm.py
remotivelabs/topology/_docs/snippets/filters.py
remotivelabs/topology/_docs/snippets/input_handlers.py
remotivelabs/topology/_docs/snippets/restbus_bm.py
remotivelabs/topology/_docs/snippets/restbus_config.py
remotivelabs/topology/_docs/snippets/restbus_namespace.py
remotivelabs/topology/_docs/snippets/restbus_namespace_set_signals.py
remotivelabs/topology/behavioral_model/__init__.py
remotivelabs/topology/behavioral_model/behavioral_model.py
remotivelabs/topology/cli/__init__.py
remotivelabs/topology/cli/behavioral_model/__init__.py
remotivelabs/topology/cli/behavioral_model/args.py
remotivelabs/topology/cli/mock/__init__.py
remotivelabs/topology/cli/mock/__main__.py
remotivelabs/topology/cli/mock/args.py
remotivelabs/topology/comm/__init__.py
remotivelabs/topology/comm/format.py
remotivelabs/topology/comm/message.py
remotivelabs/topology/comm/transport.py
remotivelabs/topology/control/__init__.py
remotivelabs/topology/control/client.py
remotivelabs/topology/control/format.py
remotivelabs/topology/control/handler.py
remotivelabs/topology/control/request.py
remotivelabs/topology/control/response.py
remotivelabs/topology/control/server.py
remotivelabs/topology/control/transport/__init__.py
remotivelabs/topology/control/transport/client.py
remotivelabs/topology/control/transport/message.py
remotivelabs/topology/control/transport/rb_transport.py
remotivelabs/topology/control/transport/server.py
remotivelabs/topology/ecu_mock.py
remotivelabs/topology/fmu/__init__.py
remotivelabs/topology/fmu/fmu.py
remotivelabs/topology/namespaces/__init__.py
remotivelabs/topology/namespaces/_conv/__init__.py
remotivelabs/topology/namespaces/_conv/some_ip_converter.py
remotivelabs/topology/namespaces/can.py
remotivelabs/topology/namespaces/filters.py
remotivelabs_topology-0.11.0.dist-info/licenses/LICENSE
remotivelabs_topology-0.11.0.dist-info/WHEEL
remotivelabs_topology-0.11.0.dist-info/METADATA
remotivelabs_topology-0.11.0.dist-info/RECORD
