Metadata-Version: 2.4
Name: remotivelabs-topology
Version: 0.11.0
Summary: RemotiveLabs RemotiveTopology framework allows developers to easily create and run ECU stubs and control their behavior
Keywords: automotive,autotech,networking,CAN
Author: Remotivelabs
Author-email: Remotivelabs <support@remotivelabs.com>
License-File: LICENSE
Classifier: Development Status :: 4 - Beta
Classifier: Intended Audience :: Developers
Classifier: Intended Audience :: Manufacturing
Classifier: Intended Audience :: Science/Research
Classifier: License :: Other/Proprietary License
Classifier: Operating System :: OS Independent
Classifier: Programming Language :: Python
Classifier: Programming Language :: Python :: 3.10
Classifier: Programming Language :: Python :: 3.11
Classifier: Programming Language :: Python :: 3.12
Classifier: Programming Language :: Python :: 3.13
Classifier: Programming Language :: Python :: 3.14
Classifier: Topic :: Communications
Classifier: Topic :: Internet
Classifier: Topic :: Scientific/Engineering :: Information Analysis
Requires-Dist: remotivelabs-broker~=0.11.0
Requires-Dist: typing-extensions~=4.13
Requires-Dist: pyhamcrest~=2.1
Requires-Dist: tenacity~=9.0
Requires-Dist: fmpy>=0.3.22 ; extra == 'fmu'
Requires-Dist: numpy>=2.2.1 ; extra == 'fmu'
Requires-Python: >=3.10, <4.0
Project-URL: Documentation, https://docs.remotivelabs.com/apis/python/remotivelabs/topology
Project-URL: Examples, https://github.com/remotivelabs/remotivelabs-topology-examples
Project-URL: Homepage, https://remotivelabs.com/
Provides-Extra: fmu
